ncbi_refseq_accession_offsets/__init__.py
ncbi_refseq_accession_offsets/db.marisa
ncbi_refseq_accession_offsets/version.py
ncbi_refseq_accession_offsets-2024.9.7.dist-info/METADATA
ncbi_refseq_accession_offsets-2024.9.7.dist-info/WHEEL
ncbi_refseq_accession_offsets-2024.9.7.dist-info/top_level.txt
ncbi_refseq_accession_offsets-2024.9.7.dist-info/RECORD
